<?xml version="1.0" encoding="UTF-8"?>
<adm:administrative-users xmlns:adm="http://pingidentity.com/2006/01/admin-users">
    <adm:user>
        <adm:user-name>administrator</adm:user-name>
        <adm:salt/>
        <adm:hash>HDmiKn4pif1XZ3UL31cqXacJT2o5Ozcg-KtoMcoMjzM.U0mdo8Da.2</adm:hash>
        <adm:phone-number xsi:nil="true" xmlns:xsi="http://www.w3.org/2001/XMLSchema-instance"/>
        <adm:email-address xsi:nil="true" xmlns:xsi="http://www.w3.org/2001/XMLSchema-instance"/>
        <adm:department xsi:nil="true" xmlns:xsi="http://www.w3.org/2001/XMLSchema-instance"/>
        <adm:description>Initial administrator user.</adm:description>
        <adm:admin-manager>true</adm:admin-manager>
        <adm:admin>true</adm:admin>
        <adm:crypto-manager>true</adm:crypto-manager>
        <adm:auditor>false</adm:auditor>
        <adm:active>true</adm:active>
        <adm:password-change-required>false</adm:password-change-required>
    </adm:user>
    <adm:user>
        <adm:user-name>test</adm:user-name>
        <adm:salt/>
        <adm:hash>URpbtZ2S23UBibNtfX1CbPiuib6UscalmS8R56IsE-4.NwXa8L4G.2</adm:hash>
        <adm:phone-number/>
        <adm:email-address/>
        <adm:department/>
        <adm:description/>
        <adm:admin-manager>false</adm:admin-manager>
        <adm:admin>false</adm:admin>
        <adm:crypto-manager>false</adm:crypto-manager>
        <adm:auditor>true</adm:auditor>
        <adm:active>true</adm:active>
        <adm:password-change-required>false</adm:password-change-required>
    </adm:user>
</adm:administrative-users>